dashstan/__init__.py
dashstan/dashstan.py
dashstan/dashstantab.py
dashstan/diagnostics/__init__.py
dashstan/diagnostics/by_model_parameter.py
dashstan/diagnostics/diagnostics.py
dashstan/diagnostics/divergence_information.py
dashstan/diagnostics/sample_information.py
dashstan/diagnostics/step_size_information.py
dashstan/diagnostics/treedepth_information.py
dashstan/estimate/__init__.py
dashstan/estimate/estimate.py
dashstan/estimate/parameters_plot.py
dashstan/estimate/post_summary_stats.py
dashstan-0.1.0.dist-info/LICENSE.txt
dashstan-0.1.0.dist-info/METADATA
dashstan-0.1.0.dist-info/WHEEL
dashstan-0.1.0.dist-info/top_level.txt
dashstan-0.1.0.dist-info/RECORD
